military_symbol/OFL.txt
military_symbol/Roboto.ttf
military_symbol/__init__.py
military_symbol/command_line.py
military_symbol/constants_parser.py
military_symbol/drawing_items.py
military_symbol/font_rendering.py
military_symbol/name_combiner.py
military_symbol/name_to_sidc.py
military_symbol/output_style.py
military_symbol/schema.py
military_symbol/symbol.py
military_symbol/symbol_cache.py
military_symbol/template.py
military_symbol/schema/activities.json
military_symbol/schema/air.json
military_symbol/schema/air_missile.json
military_symbol/schema/common_modifiers.json
military_symbol/schema/constants.json
military_symbol/schema/cyberspace.json
military_symbol/schema/dismounted_individual.json
military_symbol/schema/land_civilian.json
military_symbol/schema/land_equipment.json
military_symbol/schema/land_installations.json
military_symbol/schema/land_unit.json
military_symbol/schema/mine_warfare.json
military_symbol/schema/sea_subsurface.json
military_symbol/schema/sea_surface.json
military_symbol/schema/signals_intelligence.json
military_symbol/schema/space.json
military_symbol/schema/space_missile.json
military_symbol-2.0.8.dist-info/METADATA
military_symbol-2.0.8.dist-info/WHEEL
military_symbol-2.0.8.dist-info/entry_points.txt
military_symbol-2.0.8.dist-info/licenses/LICENSE.txt
military_symbol-2.0.8.dist-info/RECORD
