Metadata-Version: 2.4
Name: military-symbol
Version: 2.0.8
Summary: A lightweight library for producing SVGs of NATO standard military symbols from NATO sidcs or natural-language descriptions
Project-URL: Homepage, https://github.com/nwroyer/Python-Military-Symbols
Project-URL: Issues, https://github.com/nwroyer/Python-Military-Symbols/issues
Author-email: Nicholas Royer <nick.w.royer@protonmail.com>
License-Expression: MIT
License-File: LICENSE.txt
Classifier: Development Status :: 5 - Production/Stable
Classifier: License :: OSI Approved :: MIT License
Classifier: Natural Language :: English
Classifier: Operating System :: OS Independent
Classifier: Programming Language :: Python :: 3
Classifier: Topic :: Multimedia :: Graphics
Classifier: Topic :: Scientific/Engineering :: GIS
Requires-Python: >=3.13
Requires-Dist: freetype-py
Requires-Dist: lxml
Requires-Dist: pyyaml
Requires-Dist: svgpathtools
Requires-Dist: thefuzz
